pycompatibility/__init__.py
pycompatibility/__main__.py
pycompatibility/cli.py
pycompatibility/version.py
pycompatibility-1.0.0.dist-info/LICENSE
pycompatibility-1.0.0.dist-info/METADATA
pycompatibility-1.0.0.dist-info/WHEEL
pycompatibility-1.0.0.dist-info/entry_points.txt
pycompatibility-1.0.0.dist-info/top_level.txt
pycompatibility-1.0.0.dist-info/RECORD
